onebullex/__init__.py
onebullex/client.py
onebullex/auth/__init__.py
onebullex/auth/signer.py
onebullex/config/__init__.py
onebullex/config/default.py
onebullex/endpoints/__init__.py
onebullex/endpoints/account.py
onebullex/endpoints/base.py
onebullex/endpoints/market.py
onebullex/endpoints/orders.py
onebullex/errors/__init__.py
onebullex/rate_limit/__init__.py
onebullex/utils/__init__.py
onebullex-1.0.0.dist-info/METADATA
onebullex-1.0.0.dist-info/WHEEL
onebullex-1.0.0.dist-info/top_level.txt
onebullex-1.0.0.dist-info/RECORD
