Metadata-Version: 2.4
Name: onebullex
Version: 1.0.0
Summary: A production-ready Python client for the OneBullEx Exchange API
Home-page: https://github.com/FarhanKardan/OneBullex_python
Author: Farhan Kardan
Classifier: Programming Language :: Python :: 3
Classifier: License :: OSI Approved :: MIT License
Classifier: Operating System :: OS Independent
Classifier: Topic :: Software Development :: Libraries :: Python Modules
Classifier: Topic :: Office/Business :: Financial :: Investment
Requires-Python: >=3.7
Requires-Dist: requests>=2.25.0
Requires-Dist: websocket-client>=1.3.0
Requires-Dist: protobuf>=3.19.0
Requires-Dist: pydantic>=2.0.0
Requires-Dist: grpcio-tools
Dynamic: author
Dynamic: classifier
Dynamic: description
Dynamic: description-content-type
Dynamic: home-page
Dynamic: requires-dist
Dynamic: requires-python
Dynamic: summary
